dayforce_client/__init__.py
dayforce_client/client.py
dayforce_client/response.py
dayforce_client/version.py
dayforce_client-2.0.0.dist-info/LICENSE
dayforce_client-2.0.0.dist-info/METADATA
dayforce_client-2.0.0.dist-info/WHEEL
dayforce_client-2.0.0.dist-info/top_level.txt
dayforce_client-2.0.0.dist-info/RECORD
