Metadata-Version: 2.1
Name: dayforce-client
Version: 2.0.0
Summary: A python client for typed interactions with the Dayforce API.
Home-page: https://github.com/goodeggs/dayforce_client
Author: David Wallace
Author-email: david.wallace@goodeggs.com
License: MIT
Keywords: dayforce python
Classifier: License :: OSI Approved :: MIT License
Classifier: Development Status :: 5 - Production/Stable
Classifier: Natural Language :: English
Classifier: Topic :: Software Development
Classifier: Intended Audience :: Developers
Classifier: Operating System :: OS Independent
Classifier: Programming Language :: Python :: 3 :: Only
Classifier: Programming Language :: Python :: 3.6
Classifier: Programming Language :: Python :: 3.7
Classifier: Programming Language :: Python :: 3.8
Requires-Python: >=3.6
License-File: LICENSE
Requires-Dist: requests
Requires-Dist: attrs
Requires-Dist: pysftp
Requires-Dist: paramiko
Requires-Dist: cryptography
